django_shibboleth_remoteuser-0.12.data/data/shibboleth/templates/shibboleth/user_info.html
shibboleth/__init__.py
shibboleth/app_settings.py
shibboleth/backends.py
shibboleth/context_processors.py
shibboleth/decorators.py
shibboleth/middleware.py
shibboleth/models.py
shibboleth/urls.py
shibboleth/views.py
shibboleth/templates/shibboleth/user_info.html
shibboleth/tests/__init__.py
shibboleth/tests/test_shib.py
django_shibboleth_remoteuser-0.12.dist-info/METADATA
django_shibboleth_remoteuser-0.12.dist-info/WHEEL
django_shibboleth_remoteuser-0.12.dist-info/top_level.txt
django_shibboleth_remoteuser-0.12.dist-info/RECORD
