Metadata-Version: 2.1
Name: django-shibboleth-remoteuser
Version: 0.12
Summary: UNKNOWN
Home-page: https://github.com/Brown-University-Library/django-shibboleth-remoteuser
Author: Brown University Library
Author-email: bdr@brown.edu
License: UNKNOWN
Platform: UNKNOWN
Classifier: Programming Language :: Python :: 3
Classifier: License :: OSI Approved :: MIT License
Classifier: Operating System :: OS Independent
